Workbook

Sheet Dashboard
B2: KOLLEKT.GG FINANCIAL TRACKER
B3: Pokemon TCG — Version 26.0
B5: NET POSITION | D5: TOTAL INVESTED | F5: TOTAL REVENUE | H5: ROI % | J5: ITEMS IN STOCK
B6: =Sales!S2-Purchases!J2 -> 39.6375 | D6: =Purchases!J2 -> 192.6 | F6: =Sales!S2 -> 232.2375 | H6: =IFERROR((Sales!S2-Purchases!J2)/Purchases!J2,0) -> 0.20580218 | J6: =COUNTIF(Purchases!H:H,"In Stock")+COUNTIF(Purchases!H:H,"Listed") -> 3
B9: PROFIT & LOSS | F9: SPENDING BREAKDOWN
B10: Total Revenue (Gross Sales) | C10: =IFERROR(SUMPRODUCT((LEN(Sales!E4:E1000)>0)*(Sales!G4:G1000*1)),0) -> 285 | F10: Sealed Products | G10: =SUMIFS(Purchases!I4:I1000,Purchases!C4:C1000,"Sealed Product") -> 115.85
B11: Less: Platform Fees | C11: =-IFERROR(SUMPRODUCT((LEN(Sales!E4:E1000)>0)*(Sales!I4:I1000*1)),0) -> -37.7625 | F11: Single Card Purchases | G11: =SUMIFS(Purchases!I4:I1000,Purchases!C4:C1000,"Single Card") -> 17.3
B12: Less: Shipping Costs (Sales) | C12: =-IFERROR(SUMPRODUCT((LEN(Sales!E4:E1000)>0)*(Sales!J4:J1000*1)),0) -> -15 | F12: Graded Card Purchases | G12: =SUMIFS(Purchases!I4:I1000,Purchases!C4:C1000,"Graded Card") -> 0
B13: Net Sales Revenue | C13: =C10+C11+C12 -> 232.2375 | F13: Supplies (Sleeves, Toploaders, etc) | G13: =SUMIFS(Purchases!I4:I1000,Purchases!C4:C1000,"Supplies") -> 14.45
F14: Shipping Materials | G14: =SUMIFS(Purchases!I4:I1000,Purchases!C4:C1000,"Shipping Materials") -> 0
B15: Cost of Goods Sold (COGS) | C15: =-IFERROR(SUMPRODUCT((LEN(Sales!E4:E1000)>0)*(Sales!L4:L1000*1)),0) -> -8.65 | F15: Grading Fees | G15: =SUMIFS(Purchases!I4:I1000,Purchases!C4:C1000,"Grading Fees") -> 45
B16: GROSS PROFIT | C16: =C13+C15 -> 223.5875 | F16: Other Expenses | G16: =SUMIFS(Purchases!I4:I1000,Purchases!C4:C1000,"Other Expense") -> 0
B18: Grading Fees | C18: =-SUMIFS(Purchases!I4:I1000,Purchases!C4:C1000,"Grading Fees") -> -45 | F18: TOTAL SPENDING | G18: =SUM(G10:G16) -> 192.6
B19: Supplies & Materials | C19: =-(SUMIFS(Purchases!I4:I1000,Purchases!C4:C1000,"Supplies")+SUMIFS(Purchases!I4:I1000,Purchases!C4:C1000,"Shipping Materials")) -> -14.45
B20: Other Expenses | C20: =-SUMIFS(Purchases!I4:I1000,Purchases!C4:C1000,"Other Expense") -> 0 | F20: Inventory Value (At Cost) | G20: =IFERROR(SUMPRODUCT((Purchases!H4:H1000="In Stock")*(Purchases!I4:I1000*1)),0)+IFERROR(SUMPRODUCT((Purchases!H4:H1000="Listed")*(Purchases!I4:I1000*1)),0) -> 107.25
B21: Total Operating Expenses | C21: =C18+C19+C20 -> -59.45 | F21: Items Sold | G21: =COUNTA(Sales!E4:E1000)-COUNTBLANK(Sales!E4:E1000) -> -995
F22: Items In Stock | G22: =COUNTIF(Purchases!H4:H1000,"In Stock")+COUNTIF(Purchases!H4:H1000,"Listed") -> 3
B23: NET PROFIT / (LOSS) | C23: =C16+C21 -> 164.1375 | F23: Avg Profit Per Sale | G23: =IFERROR(C23/G21,0) -> -0.16496231
B26: SALES BY PLATFORM | F26: MONTHLY TREND (Last 6 Months)
B27: eBay AU | C27: =COUNTIF(Sales!H4:H1000,B27) -> 1 | D27: =SUMIFS(Sales!K4:K1000,Sales!H4:H1000,B27) -> 232.2375 | F27: Month | G27: Purchases | H27: Sales | I27: Fees | J27: Net P/L | K27: Cum. P/L
B28: eBay US | C28: =COUNTIF(Sales!H4:H1000,B28) -> 0 | D28: =SUMIFS(Sales!K4:K1000,Sales!H4:H1000,B28) -> 0 | F28: =TEXT(EDATE(TODAY(),-5),"MMM YYYY") -> Sep 2025 | G28: =IFERROR(SUMPRODUCT((MONTH(Purchases!B4:B1000)=MONTH(EDATE(TODAY(),-5)))*(YEAR(Purchases!B4:B1000)=YEAR(EDATE(TODAY(),-5)))*(Purchases!I4:I1000*1)),0) -> 0 | H28: =IFERROR(SUMPRODUCT((MONTH(Sales!B4:B1000)=MONTH(EDATE(TODAY(),-5)))*(YEAR(Sales!B4:B1000)=YEAR(EDATE(TODAY(),-5)))*(Sales!K4:K1000*1)),0) -> 0 | I28: =IFERROR(SUMPRODUCT((MONTH(Sales!B4:B1000)=MONTH(EDATE(TODAY(),-5)))*(YEAR(Sales!B4:B1000)=YEAR(EDATE(TODAY(),-5)))*(Sales!I4:I1000*1)),0) -> 0 | J28: =H28-G28-I28 -> 0 | K28: =J28 -> 0
B29: Whatnot | C29: =COUNTIF(Sales!H4:H1000,B29) -> 0 | D29: =SUMIFS(Sales!K4:K1000,Sales!H4:H1000,B29) -> 0 | F29: =TEXT(EDATE(TODAY(),-4),"MMM YYYY") -> Oct 2025 | G29: =IFERROR(SUMPRODUCT((MONTH(Purchases!B4:B1000)=MONTH(EDATE(TODAY(),-4)))*(YEAR(Purchases!B4:B1000)=YEAR(EDATE(TODAY(),-4)))*(Purchases!I4:I1000*1)),0) -> 0 | H29: =IFERROR(SUMPRODUCT((MONTH(Sales!B4:B1000)=MONTH(EDATE(TODAY(),-4)))*(YEAR(Sales!B4:B1000)=YEAR(EDATE(TODAY(),-4)))*(Sales!K4:K1000*1)),0) -> 0 | I29: =IFERROR(SUMPRODUCT((MONTH(Sales!B4:B1000)=MONTH(EDATE(TODAY(),-4)))*(YEAR(Sales!B4:B1000)=YEAR(EDATE(TODAY(),-4)))*(Sales!I4:I1000*1)),0) -> 0 | J29: =H29-G29-I29 -> 0 | K29: =K28+J29 -> 0
B30: Facebook Marketplace | C30: =COUNTIF(Sales!H4:H1000,B30) -> 0 | D30: =SUMIFS(Sales!K4:K1000,Sales!H4:H1000,B30) -> 0 | F30: =TEXT(EDATE(TODAY(),-3),"MMM YYYY") -> Nov 2025 | G30: =IFERROR(SUMPRODUCT((MONTH(Purchases!B4:B1000)=MONTH(EDATE(TODAY(),-3)))*(YEAR(Purchases!B4:B1000)=YEAR(EDATE(TODAY(),-3)))*(Purchases!I4:I1000*1)),0) -> 0 | H30: =IFERROR(SUMPRODUCT((MONTH(Sales!B4:B1000)=MONTH(EDATE(TODAY(),-3)))*(YEAR(Sales!B4:B1000)=YEAR(EDATE(TODAY(),-3)))*(Sales!K4:K1000*1)),0) -> 0 | I30: =IFERROR(SUMPRODUCT((MONTH(Sales!B4:B1000)=MONTH(EDATE(TODAY(),-3)))*(YEAR(Sales!B4:B1000)=YEAR(EDATE(TODAY(),-3)))*(Sales!I4:I1000*1)),0) -> 0 | J30: =H30-G30-I30 -> 0 | K30: =K29+J30 -> 0
B31: TCGPlayer | C31: =COUNTIF(Sales!H4:H1000,B31) -> 0 | D31: =SUMIFS(Sales!K4:K1000,Sales!H4:H1000,B31) -> 0 | F31: =TEXT(EDATE(TODAY(),-2),"MMM YYYY") -> Dec 2025 | G31: =IFERROR(SUMPRODUCT((MONTH(Purchases!B4:B1000)=MONTH(EDATE(TODAY(),-2)))*(YEAR(Purchases!B4:B1000)=YEAR(EDATE(TODAY(),-2)))*(Purchases!I4:I1000*1)),0) -> 0 | H31: =IFERROR(SUMPRODUCT((MONTH(Sales!B4:B1000)=MONTH(EDATE(TODAY(),-2)))*(YEAR(Sales!B4:B1000)=YEAR(EDATE(TODAY(),-2)))*(Sales!K4:K1000*1)),0) -> 0 | I31: =IFERROR(SUMPRODUCT((MONTH(Sales!B4:B1000)=MONTH(EDATE(TODAY(),-2)))*(YEAR(Sales!B4:B1000)=YEAR(EDATE(TODAY(),-2)))*(Sales!I4:I1000*1)),0) -> 0 | J31: =H31-G31-I31 -> 0 | K31: =K30+J31 -> 0
B32: Gumtree | C32: =COUNTIF(Sales!H4:H1000,B32) -> 0 | D32: =SUMIFS(Sales!K4:K1000,Sales!H4:H1000,B32) -> 0 | F32: =TEXT(EDATE(TODAY(),-1),"MMM YYYY") -> Jan 2026 | G32: =IFERROR(SUMPRODUCT((MONTH(Purchases!B4:B1000)=MONTH(EDATE(TODAY(),-1)))*(YEAR(Purchases!B4:B1000)=YEAR(EDATE(TODAY(),-1)))*(Purchases!I4:I1000*1)),0) -> 0 | H32: =IFERROR(SUMPRODUCT((MONTH(Sales!B4:B1000)=MONTH(EDATE(TODAY(),-1)))*(YEAR(Sales!B4:B1000)=YEAR(EDATE(TODAY(),-1)))*(Sales!K4:K1000*1)),0) -> 0 | I32: =IFERROR(SUMPRODUCT((MONTH(Sales!B4:B1000)=MONTH(EDATE(TODAY(),-1)))*(YEAR(Sales!B4:B1000)=YEAR(EDATE(TODAY(),-1)))*(Sales!I4:I1000*1)),0) -> 0 | J32: =H32-G32-I32 -> 0 | K32: =K31+J32 -> 0
B33: Mercari | C33: =COUNTIF(Sales!H4:H1000,B33) -> 0 | D33: =SUMIFS(Sales!K4:K1000,Sales!H4:H1000,B33) -> 0 | F33: =TEXT(EDATE(TODAY(),-0),"MMM YYYY") -> Feb 2026 | G33: =IFERROR(SUMPRODUCT((MONTH(Purchases!B4:B1000)=MONTH(EDATE(TODAY(),-0)))*(YEAR(Purchases!B4:B1000)=YEAR(EDATE(TODAY(),-0)))*(Purchases!I4:I1000*1)),0) -> 192.6 | H33: =IFERROR(SUMPRODUCT((MONTH(Sales!B4:B1000)=MONTH(EDATE(TODAY(),-0)))*(YEAR(Sales!B4:B1000)=YEAR(EDATE(TODAY(),-0)))*(Sales!K4:K1000*1)),0) -> 232.2375 | I33: =IFERROR(SUMPRODUCT((MONTH(Sales!B4:B1000)=MONTH(EDATE(TODAY(),-0)))*(YEAR(Sales!B4:B1000)=YEAR(EDATE(TODAY(),-0)))*(Sales!I4:I1000*1)),0) -> 37.7625 | J33: =H33-G33-I33 -> 1.875 | K33: =K32+J33 -> 1.875
B34: CardMarket | C34: =COUNTIF(Sales!H4:H1000,B34) -> 0 | D34: =SUMIFS(Sales!K4:K1000,Sales!H4:H1000,B34) -> 0
B35: Direct/Local | C35: =COUNTIF(Sales!H4:H1000,B35) -> 0 | D35: =SUMIFS(Sales!K4:K1000,Sales!H4:H1000,B35) -> 0
B36: Other | C36: =COUNTIF(Sales!H4:H1000,B36) -> 0 | D36: =SUMIFS(Sales!K4:K1000,Sales!H4:H1000,B36) -> 0
B40: kollekt.gg — The Everyday Australian Collector | Data refreshes automatically from Purchases & Sales tabs

Sheet Purchases
A1: PURCHASES — Money Out
H2: TOTAL SPENT: | J2: =SUM(I4:I1000) -> 192.6
A3: ID | B3: Date | C3: Category | D3: Description | E3: Set / Series | F3: Qty | G3: Unit Cost | H3: Status | I3: Total Cost | J3: Source | K3: Parent ID | L3: Notes | M3: Market Price | N3: Market Value
A4: =IF(B4="","",ROW()-3) -> 1 | B4: 46054 | C4: Sealed Product | D4: Ascended Heroes ETB | E4: Ascended Heroes | F4: 1 | G4: 89.95 | H4: In Stock | I4: =IF(F4="",0,F4*G4) -> 89.95 | J4: EB Games | L4: First ETB for content | N4: =IF(AND(M4<>"",F4<>""),F4*M4,"")
A5: =IF(B5="","",ROW()-3) -> 2 | B5: 46054 | C5: Sealed Product | D5: Ascended Heroes Mini Tin x2 | E5: Ascended Heroes | F5: 2 | G5: 12.95 | H5: Opened | I5: =IF(F5="",0,F5*G5) -> 25.9 | J5: Good Games | L5: Opened on camera | N5: =IF(AND(M5<>"",F5<>""),F5*M5,"")
A6: =IF(B6="","",ROW()-3) -> 3 | B6: 46056 | C6: Single Card | D6: Erika Full Art SAR | E6: Ascended Heroes | F6: 1 | G6: 8.65 | H6: Listed | I6: =IF(F6="",0,F6*G6) -> 8.65 | J6: Pulled from Mini Tin | K6: 2 | L6: Parent: Mini Tin purchase | N6: =IF(AND(M6<>"",F6<>""),F6*M6,"")
A7: =IF(B7="","",ROW()-3) -> 4 | B7: 46056 | C7: Single Card | D7: Charizard ex | E7: Ascended Heroes | F7: 1 | G7: 8.65 | H7: In Stock | I7: =IF(F7="",0,F7*G7) -> 8.65 | J7: Pulled from Mini Tin | K7: 2 | L7: Parent: Mini Tin purchase | N7: =IF(AND(M7<>"",F7<>""),F7*M7,"")
A8: =IF(B8="","",ROW()-3) -> 5 | B8: 46058 | C8: Supplies | D8: Ultra Pro Penny Sleeves (100) | F8: 1 | G8: 5.5 | H8: Used | I8: =IF(F8="",0,F8*G8) -> 5.5 | J8: Amazon AU | N8: =IF(AND(M8<>"",F8<>""),F8*M8,"")
A9: =IF(B9="","",ROW()-3) -> 6 | B9: 46058 | C9: Supplies | D9: Ultra Pro Toploaders (25) | F9: 1 | G9: 8.95 | H9: Used | I9: =IF(F9="",0,F9*G9) -> 8.95 | J9: Amazon AU | N9: =IF(AND(M9<>"",F9<>""),F9*M9,"")
A10: =IF(B10="","",ROW()-3) -> 7 | B10: 46063 | C10: Grading Fees | D10: PSA Grading - Erika SAR | F10: 1 | G10: 45 | H10: Used | I10: =IF(F10="",0,F10*G10) -> 45 | J10: PSA | K10: 3 | L10: Submitted for grading | N10: =IF(AND(M10<>"",F10<>""),F10*M10,"")
A11: =IF(B11="","",ROW()-3) | I11: =IF(F11="",0,F11*G11) -> 0 | N11: =IF(AND(M11<>"",F11<>""),F11*M11,"")
A12: =IF(B12="","",ROW()-3) | I12: =IF(F12="",0,F12*G12) -> 0 | N12: =IF(AND(M12<>"",F12<>""),F12*M12,"")
A13: =IF(B13="","",ROW()-3) | I13: =IF(F13="",0,F13*G13) -> 0 | N13: =IF(AND(M13<>"",F13<>""),F13*M13,"")
A14: =IF(B14="","",ROW()-3) | I14: =IF(F14="",0,F14*G14) -> 0 | N14: =IF(AND(M14<>"",F14<>""),F14*M14,"")
A15: =IF(B15="","",ROW()-3) | I15: =IF(F15="",0,F15*G15) -> 0 | N15: =IF(AND(M15<>"",F15<>""),F15*M15,"")
A16: =IF(B16="","",ROW()-3) | I16: =IF(F16="",0,F16*G16) -> 0 | N16: =IF(AND(M16<>"",F16<>""),F16*M16,"")
A17: =IF(B17="","",ROW()-3) | I17: =IF(F17="",0,F17*G17) -> 0 | N17: =IF(AND(M17<>"",F17<>""),F17*M17,"")
A18: =IF(B18="","",ROW()-3) | I18: =IF(F18="",0,F18*G18) -> 0 | N18: =IF(AND(M18<>"",F18<>""),F18*M18,"")
A19: =IF(B19="","",ROW()-3) | I19: =IF(F19="",0,F19*G19) -> 0 | N19: =IF(AND(M19<>"",F19<>""),F19*M19,"")
A20: =IF(B20="","",ROW()-3) | I20: =IF(F20="",0,F20*G20) -> 0 | N20: =IF(AND(M20<>"",F20<>""),F20*M20,"")
A21: =IF(B21="","",ROW()-3) | I21: =IF(F21="",0,F21*G21) -> 0 | N21: =IF(AND(M21<>"",F21<>""),F21*M21,"")
A22: =IF(B22="","",ROW()-3) | I22: =IF(F22="",0,F22*G22) -> 0 | N22: =IF(AND(M22<>"",F22<>""),F22*M22,"")
... A1000: =IF(B1000="","",ROW()-3) | I1000: =IF(F1000="",0,F1000*G1000) -> 0 | N1000: =IF(AND(M1000<>"",F1000<>""),F1000*M1000,"")

Sheet Sales
A1: SALES — Money In
R2: NET REVENUE: | S2: =SUM(K4:K1000) -> 232.2375
A3: ID | B3: Date Sold | C3: Category | D3: Description | E3: Set / Series | F3: Qty | G3: Sale Price | H3: Platform | I3: Platform Fee $ | J3: Shipping Cost | K3: Net Revenue | L3: COGS | M3: Profit / Loss | N3: Margin % | O3: Purchase Ref ID | P3: Buyer | Q3: Tracking # | R3: Notes | S3: Fee % Used
A4: =IF(B4="","",ROW()-3) -> 1 | B4: 46068 | C4: Graded Card | D4: Erika Full Art SAR PSA 10 | E4: Ascended Heroes | F4: 1 | G4: 285 | H4: eBay AU | I4: =IF(G4="",0,G4*S4) -> 37.7625 | J4: 15 | K4: =IF(G4="",0,G4-I4-IF(J4="",0,J4)) -> 232.2375 | L4: =IF(O4="",0,IFERROR(INDEX(Purchases!I:I,MATCH(O4*1,Purchases!A:A,0)),0)) -> 8.65 | M4: =IF(G4="",0,K4-L4) -> 223.5875 | N4: =IFERROR(IF(G4="","",M4/G4),"") -> 0.78451754 | O4: 3 | P4: PokeFan123 | Q4: AU1234567890 | R4: First big sale! | S4: =IFERROR(VLOOKUP(H4,Settings!B14:C25,2,FALSE()),0) -> 0.1325
A5: =IF(B5="","",ROW()-3) | I5: =IF(G5="",0,G5*S5) -> 0 | K5: =IF(G5="",0,G5-I5-IF(J5="",0,J5)) -> 0 | L5: =IF(O5="",0,IFERROR(INDEX(Purchases!I:I,MATCH(O5*1,Purchases!A:A,0)),0)) -> 0 | M5: =IF(G5="",0,K5-L5) -> 0 | N5: =IFERROR(IF(G5="","",M5/G5),"") | S5: =IFERROR(VLOOKUP(H5,Settings!B14:C25,2,FALSE()),0) -> 0
A6: =IF(B6="","",ROW()-3) | I6: =IF(G6="",0,G6*S6) -> 0 | K6: =IF(G6="",0,G6-I6-IF(J6="",0,J6)) -> 0 | L6: =IF(O6="",0,IFERROR(INDEX(Purchases!I:I,MATCH(O6*1,Purchases!A:A,0)),0)) -> 0 | M6: =IF(G6="",0,K6-L6) -> 0 | N6: =IFERROR(IF(G6="","",M6/G6),"") | S6: =IFERROR(VLOOKUP(H6,Settings!B14:C25,2,FALSE()),0) -> 0
A7: =IF(B7="","",ROW()-3) | I7: =IF(G7="",0,G7*S7) -> 0 | K7: =IF(G7="",0,G7-I7-IF(J7="",0,J7)) -> 0 | L7: =IF(O7="",0,IFERROR(INDEX(Purchases!I:I,MATCH(O7*1,Purchases!A:A,0)),0)) -> 0 | M7: =IF(G7="",0,K7-L7) -> 0 | N7: =IFERROR(IF(G7="","",M7/G7),"") | S7: =IFERROR(VLOOKUP(H7,Settings!B14:C25,2,FALSE()),0) -> 0
A8: =IF(B8="","",ROW()-3) | I8: =IF(G8="",0,G8*S8) -> 0 | K8: =IF(G8="",0,G8-I8-IF(J8="",0,J8)) -> 0 | L8: =IF(O8="",0,IFERROR(INDEX(Purchases!I:I,MATCH(O8*1,Purchases!A:A,0)),0)) -> 0 | M8: =IF(G8="",0,K8-L8) -> 0 | N8: =IFERROR(IF(G8="","",M8/G8),"") | S8: =IFERROR(VLOOKUP(H8,Settings!B14:C25,2,FALSE()),0) -> 0
A9: =IF(B9="","",ROW()-3) | I9: =IF(G9="",0,G9*S9) -> 0 | K9: =IF(G9="",0,G9-I9-IF(J9="",0,J9)) -> 0 | L9: =IF(O9="",0,IFERROR(INDEX(Purchases!I:I,MATCH(O9*1,Purchases!A:A,0)),0)) -> 0 | M9: =IF(G9="",0,K9-L9) -> 0 | N9: =IFERROR(IF(G9="","",M9/G9),"") | S9: =IFERROR(VLOOKUP(H9,Settings!B14:C25,2,FALSE()),0) -> 0
A10: =IF(B10="","",ROW()-3) | I10: =IF(G10="",0,G10*S10) -> 0 | K10: =IF(G10="",0,G10-I10-IF(J10="",0,J10)) -> 0 | L10: =IF(O10="",0,IFERROR(INDEX(Purchases!I:I,MATCH(O10*1,Purchases!A:A,0)),0)) -> 0 | M10: =IF(G10="",0,K10-L10) -> 0 | N10: =IFERROR(IF(G10="","",M10/G10),"") | S10: =IFERROR(VLOOKUP(H10,Settings!B14:C25,2,FALSE()),0) -> 0
A11: =IF(B11="","",ROW()-3) | I11: =IF(G11="",0,G11*S11) -> 0 | K11: =IF(G11="",0,G11-I11-IF(J11="",0,J11)) -> 0 | L11: =IF(O11="",0,IFERROR(INDEX(Purchases!I:I,MATCH(O11*1,Purchases!A:A,0)),0)) -> 0 | M11: =IF(G11="",0,K11-L11) -> 0 | N11: =IFERROR(IF(G11="","",M11/G11),"") | S11: =IFERROR(VLOOKUP(H11,Settings!B14:C25,2,FALSE()),0) -> 0
A12: =IF(B12="","",ROW()-3) | I12: =IF(G12="",0,G12*S12) -> 0 | K12: =IF(G12="",0,G12-I12-IF(J12="",0,J12)) -> 0 | L12: =IF(O12="",0,IFERROR(INDEX(Purchases!I:I,MATCH(O12*1,Purchases!A:A,0)),0)) -> 0 | M12: =IF(G12="",0,K12-L12) -> 0 | N12: =IFERROR(IF(G12="","",M12/G12),"") | S12: =IFERROR(VLOOKUP(H12,Settings!B14:C25,2,FALSE()),0) -> 0
A13: =IF(B13="","",ROW()-3) | I13: =IF(G13="",0,G13*S13) -> 0 | K13: =IF(G13="",0,G13-I13-IF(J13="",0,J13)) -> 0 | L13: =IF(O13="",0,IFERROR(INDEX(Purchases!I:I,MATCH(O13*1,Purchases!A:A,0)),0)) -> 0 | M13: =IF(G13="",0,K13-L13) -> 0 | N13: =IFERROR(IF(G13="","",M13/G13),"") | S13: =IFERROR(VLOOKUP(H13,Settings!B14:C25,2,FALSE()),0) -> 0
A14: =IF(B14="","",ROW()-3) | I14: =IF(G14="",0,G14*S14) -> 0 | K14: =IF(G14="",0,G14-I14-IF(J14="",0,J14)) -> 0 | L14: =IF(O14="",0,IFERROR(INDEX(Purchases!I:I,MATCH(O14*1,Purchases!A:A,0)),0)) -> 0 | M14: =IF(G14="",0,K14-L14) -> 0 | N14: =IFERROR(IF(G14="","",M14/G14),"") | S14: =IFERROR(VLOOKUP(H14,Settings!B14:C25,2,FALSE()),0) -> 0
A15: =IF(B15="","",ROW()-3) | I15: =IF(G15="",0,G15*S15) -> 0 | K15: =IF(G15="",0,G15-I15-IF(J15="",0,J15)) -> 0 | L15: =IF(O15="",0,IFERROR(INDEX(Purchases!I:I,MATCH(O15*1,Purchases!A:A,0)),0)) -> 0 | M15: =IF(G15="",0,K15-L15) -> 0 | N15: =IFERROR(IF(G15="","",M15/G15),"") | S15: =IFERROR(VLOOKUP(H15,Settings!B14:C25,2,FALSE()),0) -> 0
A16: =IF(B16="","",ROW()-3) | I16: =IF(G16="",0,G16*S16) -> 0 | K16: =IF(G16="",0,G16-I16-IF(J16="",0,J16)) -> 0 | L16: =IF(O16="",0,IFERROR(INDEX(Purchases!I:I,MATCH(O16*1,Purchases!A:A,0)),0)) -> 0 | M16: =IF(G16="",0,K16-L16) -> 0 | N16: =IFERROR(IF(G16="","",M16/G16),"") | S16: =IFERROR(VLOOKUP(H16,Settings!B14:C25,2,FALSE()),0) -> 0
A17: =IF(B17="","",ROW()-3) | I17: =IF(G17="",0,G17*S17) -> 0 | K17: =IF(G17="",0,G17-I17-IF(J17="",0,J17)) -> 0 | L17: =IF(O17="",0,IFERROR(INDEX(Purchases!I:I,MATCH(O17*1,Purchases!A:A,0)),0)) -> 0 | M17: =IF(G17="",0,K17-L17) -> 0 | N17: =IFERROR(IF(G17="","",M17/G17),"") | S17: =IFERROR(VLOOKUP(H17,Settings!B14:C25,2,FALSE()),0) -> 0
A18: =IF(B18="","",ROW()-3) | I18: =IF(G18="",0,G18*S18) -> 0 | K18: =IF(G18="",0,G18-I18-IF(J18="",0,J18)) -> 0 | L18: =IF(O18="",0,IFERROR(INDEX(Purchases!I:I,MATCH(O18*1,Purchases!A:A,0)),0)) -> 0 | M18: =IF(G18="",0,K18-L18) -> 0 | N18: =IFERROR(IF(G18="","",M18/G18),"") | S18: =IFERROR(VLOOKUP(H18,Settings!B14:C25,2,FALSE()),0) -> 0
A19: =IF(B19="","",ROW()-3) | I19: =IF(G19="",0,G19*S19) -> 0 | K19: =IF(G19="",0,G19-I19-IF(J19="",0,J19)) -> 0 | L19: =IF(O19="",0,IFERROR(INDEX(Purchases!I:I,MATCH(O19*1,Purchases!A:A,0)),0)) -> 0 | M19: =IF(G19="",0,K19-L19) -> 0 | N19: =IFERROR(IF(G19="","",M19/G19),"") | S19: =IFERROR(VLOOKUP(H19,Settings!B14:C25,2,FALSE()),0) -> 0
A20: =IF(B20="","",ROW()-3) | I20: =IF(G20="",0,G20*S20) -> 0 | K20: =IF(G20="",0,G20-I20-IF(J20="",0,J20)) -> 0 | L20: =IF(O20="",0,IFERROR(INDEX(Purchases!I:I,MATCH(O20*1,Purchases!A:A,0)),0)) -> 0 | M20: =IF(G20="",0,K20-L20) -> 0 | N20: =IFERROR(IF(G20="","",M20/G20),"") | S20: =IFERROR(VLOOKUP(H20,Settings!B14:C25,2,FALSE()),0) -> 0
A21: =IF(B21="","",ROW()-3) | I21: =IF(G21="",0,G21*S21) -> 0 | K21: =IF(G21="",0,G21-I21-IF(J21="",0,J21)) -> 0 | L21: =IF(O21="",0,IFERROR(INDEX(Purchases!I:I,MATCH(O21*1,Purchases!A:A,0)),0)) -> 0 | M21: =IF(G21="",0,K21-L21) -> 0 | N21: =IFERROR(IF(G21="","",M21/G21),"") | S21: =IFERROR(VLOOKUP(H21,Settings!B14:C25,2,FALSE()),0) -> 0
A22: =IF(B22="","",ROW()-3) | I22: =IF(G22="",0,G22*S22) -> 0 | K22: =IF(G22="",0,G22-I22-IF(J22="",0,J22)) -> 0 | L22: =IF(O22="",0,IFERROR(INDEX(Purchases!I:I,MATCH(O22*1,Purchases!A:A,0)),0)) -> 0 | M22: =IF(G22="",0,K22-L22) -> 0 | N22: =IFERROR(IF(G22="","",M22/G22),"") | S22: =IFERROR(VLOOKUP(H22,Settings!B14:C25,2,FALSE()),0) -> 0
A23: =IF(B23="","",ROW()-3) | I23: =IF(G23="",0,G23*S23) -> 0 | K23: =IF(G23="",0,G23-I23-IF(J23="",0,J23)) -> 0 | L23: =IF(O23="",0,IFERROR(INDEX(Purchases!I:I,MATCH(O23*1,Purchases!A:A,0)),0)) -> 0 | M23: =IF(G23="",0,K23-L23) -> 0 | N23: =IFERROR(IF(G23="","",M23/G23),"") | S23: =IFERROR(VLOOKUP(H23,Settings!B14:C25,2,FALSE()),0) -> 0
A24: =IF(B24="","",ROW()-3) | I24: =IF(G24="",0,G24*S24) -> 0 | K24: =IF(G24="",0,G24-I24-IF(J24="",0,J24)) -> 0 | L24: =IF(O24="",0,IFERROR(INDEX(Purchases!I:I,MATCH(O24*1,Purchases!A:A,0)),0)) -> 0 | M24: =IF(G24="",0,K24-L24) -> 0 | N24: =IFERROR(IF(G24="","",M24/G24),"") | S24: =IFERROR(VLOOKUP(H24,Settings!B14:C25,2,FALSE()),0) -> 0
A25: =IF(B25="","",ROW()-3) | I25: =IF(G25="",0,G25*S25) -> 0 | K25: =IF(G25="",0,G25-I25-IF(J25="",0,J25)) -> 0 | L25: =IF(O25="",0,IFERROR(INDEX(Purchases!I:I,MATCH(O25*1,Purchases!A:A,0)),0)) -> 0 | M25: =IF(G25="",0,K25-L25) -> 0 | N25: =IFERROR(IF(G25="","",M25/G25),"") | S25: =IFERROR(VLOOKUP(H25,Settings!B14:C25,2,FALSE()),0) -> 0
A26: =IF(B26="","",ROW()-3) | I26: =IF(G26="",0,G26*S26) -> 0 | K26: =IF(G26="",0,G26-I26-IF(J26="",0,J26)) -> 0 | L26: =IF(O26="",0,IFERROR(INDEX(Purchases!I:I,MATCH(O26*1,Purchases!A:A,0)),0)) -> 0 | M26: =IF(G26="",0,K26-L26) -> 0 | N26: =IFERROR(IF(G26="","",M26/G26),"") | S26: =IFERROR(VLOOKUP(H26,Settings!B14:C25,2,FALSE()),0) -> 0
A27: =IF(B27="","",ROW()-3) | I27: =IF(G27="",0,G27*S27) -> 0 | K27: =IF(G27="",0,G27-I27-IF(J27="",0,J27)) -> 0 | L27: =IF(O27="",0,IFERROR(INDEX(Purchases!I:I,MATCH(O27*1,Purchases!A:A,0)),0)) -> 0 | M27: =IF(G27="",0,K27-L27) -> 0 | N27: =IFERROR(IF(G27="","",M27/G27),"") | S27: =IFERROR(VLOOKUP(H27,Settings!B14:C25,2,FALSE()),0) -> 0
A28: =IF(B28="","",ROW()-3) | I28: =IF(G28="",0,G28*S28) -> 0 | K28: =IF(G28="",0,G28-I28-IF(J28="",0,J28)) -> 0 | L28: =IF(O28="",0,IFERROR(INDEX(Purchases!I:I,MATCH(O28*1,Purchases!A:A,0)),0)) -> 0 | M28: =IF(G28="",0,K28-L28) -> 0 | N28: =IFERROR(IF(G28="","",M28/G28),"") | S28: =IFERROR(VLOOKUP(H28,Settings!B14:C25,2,FALSE()),0) -> 0
A29: =IF(B29="","",ROW()-3) | I29: =IF(G29="",0,G29*S29) -> 0 | K29: =IF(G29="",0,G29-I29-IF(J29="",0,J29)) -> 0 | L29: =IF(O29="",0,IFERROR(INDEX(Purchases!I:I,MATCH(O29*1,Purchases!A:A,0)),0)) -> 0 | M29: =IF(G29="",0,K29-L29) -> 0 | N29: =IFERROR(IF(G29="","",M29/G29),"") | S29: =IFERROR(VLOOKUP(H29,Settings!B14:C25,2,FALSE()),0) -> 0
A30: =IF(B30="","",ROW()-3) | I30: =IF(G30="",0,G30*S30) -> 0 | K30: =IF(G30="",0,G30-I30-IF(J30="",0,J30)) -> 0 | L30: =IF(O30="",0,IFERROR(INDEX(Purchases!I:I,MATCH(O30*1,Purchases!A:A,0)),0)) -> 0 | M30: =IF(G30="",0,K30-L30) -> 0 | N30: =IFERROR(IF(G30="","",M30/G30),"") | S30: =IFERROR(VLOOKUP(H30,Settings!B14:C25,2,FALSE()),0) -> 0
A31: =IF(B31="","",ROW()-3) | I31: =IF(G31="",0,G31*S31) -> 0 | K31: =IF(G31="",0,G31-I31-IF(J31="",0,J31)) -> 0 | L31: =IF(O31="",0,IFERROR(INDEX(Purchases!I:I,MATCH(O31*1,Purchases!A:A,0)),0)) -> 0 | M31: =IF(G31="",0,K31-L31) -> 0 | N31: =IFERROR(IF(G31="","",M31/G31),"") | S31: =IFERROR(VLOOKUP(H31,Settings!B14:C25,2,FALSE()),0) -> 0
A32: =IF(B32="","",ROW()-3) | I32: =IF(G32="",0,G32*S32) -> 0 | K32: =IF(G32="",0,G32-I32-IF(J32="",0,J32)) -> 0 | L32: =IF(O32="",0,IFERROR(INDEX(Purchases!I:I,MATCH(O32*1,Purchases!A:A,0)),0)) -> 0 | M32: =IF(G32="",0,K32-L32) -> 0 | N32: =IFERROR(IF(G32="","",M32/G32),"") | S32: =IFERROR(VLOOKUP(H32,Settings!B14:C25,2,FALSE()),0) -> 0
A33: =IF(B33="","",ROW()-3) | I33: =IF(G33="",0,G33*S33) -> 0 | K33: =IF(G33="",0,G33-I33-IF(J33="",0,J33)) -> 0 | L33: =IF(O33="",0,IFERROR(INDEX(Purchases!I:I,MATCH(O33*1,Purchases!A:A,0)),0)) -> 0 | M33: =IF(G33="",0,K33-L33) -> 0 | N33: =IFERROR(IF(G33="","",M33/G33),"") | S33: =IFERROR(VLOOKUP(H33,Settings!B14:C25,2,FALSE()),0) -> 0
A34: =IF(B34="","",ROW()-3) | I34: =IF(G34="",0,G34*S34) -> 0 | K34: =IF(G34="",0,G34-I34-IF(J34="",0,J34)) -> 0 | L34: =IF(O34="",0,IFERROR(INDEX(Purchases!I:I,MATCH(O34*1,Purchases!A:A,0)),0)) -> 0 | M34: =IF(G34="",0,K34-L34) -> 0 | N34: =IFERROR(IF(G34="","",M34/G34),"") | S34: =IFERROR(VLOOKUP(H34,Settings!B14:C25,2,FALSE()),0) -> 0
A35: =IF(B35="","",ROW()-3) | I35: =IF(G35="",0,G35*S35) -> 0 | K35: =IF(G35="",0,G35-I35-IF(J35="",0,J35)) -> 0 | L35: =IF(O35="",0,IFERROR(INDEX(Purchases!I:I,MATCH(O35*1,Purchases!A:A,0)),0)) -> 0 | M35: =IF(G35="",0,K35-L35) -> 0 | N35: =IFERROR(IF(G35="","",M35/G35),"") | S35: =IFERROR(VLOOKUP(H35,Settings!B14:C25,2,FALSE()),0) -> 0
A36: =IF(B36="","",ROW()-3) | I36: =IF(G36="",0,G36*S36) -> 0 | K36: =IF(G36="",0,G36-I36-IF(J36="",0,J36)) -> 0 | L36: =IF(O36="",0,IFERROR(INDEX(Purchases!I:I,MATCH(O36*1,Purchases!A:A,0)),0)) -> 0 | M36: =IF(G36="",0,K36-L36) -> 0 | N36: =IFERROR(IF(G36="","",M36/G36),"") | S36: =IFERROR(VLOOKUP(H36,Settings!B14:C25,2,FALSE()),0) -> 0
A37: =IF(B37="","",ROW()-3) | I37: =IF(G37="",0,G37*S37) -> 0 | K37: =IF(G37="",0,G37-I37-IF(J37="",0,J37)) -> 0 | L37: =IF(O37="",0,IFERROR(INDEX(Purchases!I:I,MATCH(O37*1,Purchases!A:A,0)),0)) -> 0 | M37: =IF(G37="",0,K37-L37) -> 0 | N37: =IFERROR(IF(G37="","",M37/G37),"") | S37: =IFERROR(VLOOKUP(H37,Settings!B14:C25,2,FALSE()),0) -> 0
A38: =IF(B38="","",ROW()-3) | I38: =IF(G38="",0,G38*S38) -> 0 | K38: =IF(G38="",0,G38-I38-IF(J38="",0,J38)) -> 0 | L38: =IF(O38="",0,IFERROR(INDEX(Purchases!I:I,MATCH(O38*1,Purchases!A:A,0)),0)) -> 0 | M38: =IF(G38="",0,K38-L38) -> 0 | N38: =IFERROR(IF(G38="","",M38/G38),"") | S38: =IFERROR(VLOOKUP(H38,Settings!B14:C25,2,FALSE()),0) -> 0
A39: =IF(B39="","",ROW()-3) | I39: =IF(G39="",0,G39*S39) -> 0 | K39: =IF(G39="",0,G39-I39-IF(J39="",0,J39)) -> 0 | L39: =IF(O39="",0,IFERROR(INDEX(Purchases!I:I,MATCH(O39*1,Purchases!A:A,0)),0)) -> 0 | M39: =IF(G39="",0,K39-L39) -> 0 | N39: =IFERROR(IF(G39="","",M39/G39),"") | S39: =IFERROR(VLOOKUP(H39,Settings!B14:C25,2,FALSE()),0) -> 0
A40: =IF(B40="","",ROW()-3) | I40: =IF(G40="",0,G40*S40) -> 0 | K40: =IF(G40="",0,G40-I40-IF(J40="",0,J40)) -> 0 | L40: =IF(O40="",0,IFERROR(INDEX(Purchases!I:I,MATCH(O40*1,Purchases!A:A,0)),0)) -> 0 | M40: =IF(G40="",0,K40-L40) -> 0 | N40: =IFERROR(IF(G40="","",M40/G40),"") | S40: =IFERROR(VLOOKUP(H40,Settings!B14:C25,2,FALSE()),0) -> 0
A41: =IF(B41="","",ROW()-3) | I41: =IF(G41="",0,G41*S41) -> 0 | K41: =IF(G41="",0,G41-I41-IF(J41="",0,J41)) -> 0 | L41: =IF(O41="",0,IFERROR(INDEX(Purchases!I:I,MATCH(O41*1,Purchases!A:A,0)),0)) -> 0 | M41: =IF(G41="",0,K41-L41) -> 0 | N41: =IFERROR(IF(G41="","",M41/G41),"") | S41: =IFERROR(VLOOKUP(H41,Settings!B14:C25,2,FALSE()),0) -> 0
A42: =IF(B42="","",ROW()-3) | I42: =IF(G42="",0,G42*S42) -> 0 | K42: =IF(G42="",0,G42-I42-IF(J42="",0,J42)) -> 0 | L42: =IF(O42="",0,IFERROR(INDEX(Purchases!I:I,MATCH(O42*1,Purchases!A:A,0)),0)) -> 0 | M42: =IF(G42="",0,K42-L42) -> 0 | N42: =IFERROR(IF(G42="","",M42/G42),"") | S42: =IFERROR(VLOOKUP(H42,Settings!B14:C25,2,FALSE()),0) -> 0
A43: =IF(B43="","",ROW()-3) | I43: =IF(G43="",0,G43*S43) -> 0 | K43: =IF(G43="",0,G43-I43-IF(J43="",0,J43)) -> 0 | L43: =IF(O43="",0,IFERROR(INDEX(Purchases!I:I,MATCH(O43*1,Purchases!A:A,0)),0)) -> 0 | M43: =IF(G43="",0,K43-L43) -> 0 | N43: =IFERROR(IF(G43="","",M43/G43),"") | S43: =IFERROR(VLOOKUP(H43,Settings!B14:C25,2,FALSE()),0) -> 0
A44: =IF(B44="","",ROW()-3) | I44: =IF(G44="",0,G44*S44) -> 0 | K44: =IF(G44="",0,G44-I44-IF(J44="",0,J44)) -> 0 | L44: =IF(O44="",0,IFERROR(INDEX(Purchases!I:I,MATCH(O44*1,Purchases!A:A,0)),0)) -> 0 | M44: =IF(G44="",0,K44-L44) -> 0 | N44: =IFERROR(IF(G44="","",M44/G44),"") | S44: =IFERROR(VLOOKUP(H44,Settings!B14:C25,2,FALSE()),0) -> 0
A45: =IF(B45="","",ROW()-3) | I45: =IF(G45="",0,G45*S45) -> 0 | K45: =IF(G45="",0,G45-I45-IF(J45="",0,J45)) -> 0 | L45: =IF(O45="",0,IFERROR(INDEX(Purchases!I:I,MATCH(O45*1,Purchases!A:A,0)),0)) -> 0 | M45: =IF(G45="",0,K45-L45) -> 0 | N45: =IFERROR(IF(G45="","",M45/G45),"") | S45: =IFERROR(VLOOKUP(H45,Settings!B14:C25,2,FALSE()),0) -> 0
A46: =IF(B46="","",ROW()-3) | I46: =IF(G46="",0,G46*S46) -> 0 | K46: =IF(G46="",0,G46-I46-IF(J46="",0,J46)) -> 0 | L46: =IF(O46="",0,IFERROR(INDEX(Purchases!I:I,MATCH(O46*1,Purchases!A:A,0)),0)) -> 0 | M46: =IF(G46="",0,K46-L46) -> 0 | N46: =IFERROR(IF(G46="","",M46/G46),"") | S46: =IFERROR(VLOOKUP(H46,Settings!B14:C25,2,FALSE()),0) -> 0
A47: =IF(B47="","",ROW()-3) | I47: =IF(G47="",0,G47*S47) -> 0 | K47: =IF(G47="",0,G47-I47-IF(J47="",0,J47)) -> 0 | L47: =IF(O47="",0,IFERROR(INDEX(Purchases!I:I,MATCH(O47*1,Purchases!A:A,0)),0)) -> 0 | M47: =IF(G47="",0,K47-L47) -> 0 | N47: =IFERROR(IF(G47="","",M47/G47),"") | S47: =IFERROR(VLOOKUP(H47,Settings!B14:C25,2,FALSE()),0) -> 0
A48: =IF(B48="","",ROW()-3) | I48: =IF(G48="",0,G48*S48) -> 0 | K48: =IF(G48="",0,G48-I48-IF(J48="",0,J48)) -> 0 | L48: =IF(O48="",0,IFERROR(INDEX(Purchases!I:I,MATCH(O48*1,Purchases!A:A,0)),0)) -> 0 | M48: =IF(G48="",0,K48-L48) -> 0 | N48: =IFERROR(IF(G48="","",M48/G48),"") | S48: =IFERROR(VLOOKUP(H48,Settings!B14:C25,2,FALSE()),0) -> 0
A49: =IF(B49="","",ROW()-3) | I49: =IF(G49="",0,G49*S49) -> 0 | K49: =IF(G49="",0,G49-I49-IF(J49="",0,J49)) -> 0 | L49: =IF(O49="",0,IFERROR(INDEX(Purchases!I:I,MATCH(O49*1,Purchases!A:A,0)),0)) -> 0 | M49: =IF(G49="",0,K49-L49) -> 0 | N49: =IFERROR(IF(G49="","",M49/G49),"") | S49: =IFERROR(VLOOKUP(H49,Settings!B14:C25,2,FALSE()),0) -> 0
A50: =IF(B50="","",ROW()-3) | I50: =IF(G50="",0,G50*S50) -> 0 | K50: =IF(G50="",0,G50-I50-IF(J50="",0,J50)) -> 0 | L50: =IF(O50="",0,IFERROR(INDEX(Purchases!I:I,MATCH(O50*1,Purchases!A:A,0)),0)) -> 0 | M50: =IF(G50="",0,K50-L50) -> 0 | N50: =IFERROR(IF(G50="","",M50/G50),"") | S50: =IFERROR(VLOOKUP(H50,Settings!B14:C25,2,FALSE()),0) -> 0
A51: =IF(B51="","",ROW()-3) | I51: =IF(G51="",0,G51*S51) -> 0 | K51: =IF(G51="",0,G51-I51-IF(J51="",0,J51)) -> 0 | L51: =IF(O51="",0,IFERROR(INDEX(Purchases!I:I,MATCH(O51*1,Purchases!A:A,0)),0)) -> 0 | M51: =IF(G51="",0,K51-L51) -> 0 | N51: =IFERROR(IF(G51="","",M51/G51),"") | S51: =IFERROR(VLOOKUP(H51,Settings!B14:C25,2,FALSE()),0) -> 0
A52: =IF(B52="","",ROW()-3) | I52: =IF(G52="",0,G52*S52) -> 0 | K52: =IF(G52="",0,G52-I52-IF(J52="",0,J52)) -> 0 | L52: =IF(O52="",0,IFERROR(INDEX(Purchases!I:I,MATCH(O52*1,Purchases!A:A,0)),0)) -> 0 | M52: =IF(G52="",0,K52-L52) -> 0 | N52: =IFERROR(IF(G52="","",M52/G52),"") | S52: =IFERROR(VLOOKUP(H52,Settings!B14:C25,2,FALSE()),0) -> 0
A53: =IF(B53="","",ROW()-3) | I53: =IF(G53="",0,G53*S53) -> 0 | K53: =IF(G53="",0,G53-I53-IF(J53="",0,J53)) -> 0 | L53: =IF(O53="",0,IFERROR(INDEX(Purchases!I:I,MATCH(O53*1,Purchases!A:A,0)),0)) -> 0 | M53: =IF(G53="",0,K53-L53) -> 0 | N53: =IFERROR(IF(G53="","",M53/G53),"") | S53: =IFERROR(VLOOKUP(H53,Settings!B14:C25,2,FALSE()),0) -> 0
A54: =IF(B54="","",ROW()-3) | I54: =IF(G54="",0,G54*S54) -> 0 | K54: =IF(G54="",0,G54-I54-IF(J54="",0,J54)) -> 0 | L54: =IF(O54="",0,IFERROR(INDEX(Purchases!I:I,MATCH(O54*1,Purchases!A:A,0)),0)) -> 0 | M54: =IF(G54="",0,K54-L54) -> 0 | N54: =IFERROR(IF(G54="","",M54/G54),"") | S54: =IFERROR(VLOOKUP(H54,Settings!B14:C25,2,FALSE()),0) -> 0
A55: =IF(B55="","",ROW()-3) | I55: =IF(G55="",0,G55*S55) -> 0 | K55: =IF(G55="",0,G55-I55-IF(J55="",0,J55)) -> 0 | L55: =IF(O55="",0,IFERROR(INDEX(Purchases!I:I,MATCH(O55*1,Purchases!A:A,0)),0)) -> 0 | M55: =IF(G55="",0,K55-L55) -> 0 | N55: =IFERROR(IF(G55="","",M55/G55),"") | S55: =IFERROR(VLOOKUP(H55,Settings!B14:C25,2,FALSE()),0) -> 0
A56: =IF(B56="","",ROW()-3) | I56: =IF(G56="",0,G56*S56) -> 0 | K56: =IF(G56="",0,G56-I56-IF(J56="",0,J56)) -> 0 | L56: =IF(O56="",0,IFERROR(INDEX(Purchases!I:I,MATCH(O56*1,Purchases!A:A,0)),0)) -> 0 | M56: =IF(G56="",0,K56-L56) -> 0 | N56: =IFERROR(IF(G56="","",M56/G56),"") | S56: =IFERROR(VLOOKUP(H56,Settings!B14:C25,2,FALSE()),0) -> 0
A57: =IF(B57="","",ROW()-3) | I57: =IF(G57="",0,G57*S57) -> 0 | K57: =IF(G57="",0,G57-I57-IF(J57="",0,J57)) -> 0 | L57: =IF(O57="",0,IFERROR(INDEX(Purchases!I:I,MATCH(O57*1,Purchases!A:A,0)),0)) -> 0 | M57: =IF(G57="",0,K57-L57) -> 0 | N57: =IFERROR(IF(G57="","",M57/G57),"") | S57: =IFERROR(VLOOKUP(H57,Settings!B14:C25,2,FALSE()),0) -> 0
A58: =IF(B58="","",ROW()-3) | I58: =IF(G58="",0,G58*S58) -> 0 | K58: =IF(G58="",0,G58-I58-IF(J58="",0,J58)) -> 0 | L58: =IF(O58="",0,IFERROR(INDEX(Purchases!I:I,MATCH(O58*1,Purchases!A:A,0)),0)) -> 0 | M58: =IF(G58="",0,K58-L58) -> 0 | N58: =IFERROR(IF(G58="","",M58/G58),"") | S58: =IFERROR(VLOOKUP(H58,Settings!B14:C25,2,FALSE()),0) -> 0
A59: =IF(B59="","",ROW()-3) | I59: =IF(G59="",0,G59*S59) -> 0 | K59: =IF(G59="",0,G59-I59-IF(J59="",0,J59)) -> 0 | L59: =IF(O59="",0,IFERROR(INDEX(Purchases!I:I,MATCH(O59*1,Purchases!A:A,0)),0)) -> 0 | M59: =IF(G59="",0,K59-L59) -> 0 | N59: =IFERROR(IF(G59="","",M59/G59),"") | S59: =IFERROR(VLOOKUP(H59,Settings!B14:C25,2,FALSE()),0) -> 0
A60: =IF(B60="","",ROW()-3) | I60: =IF(G60="",0,G60*S60) -> 0 | K60: =IF(G60="",0,G60-I60-IF(J60="",0,J60)) -> 0 | L60: =IF(O60="",0,IFERROR(INDEX(Purchases!I:I,MATCH(O60*1,Purchases!A:A,0)),0)) -> 0 | M60: =IF(G60="",0,K60-L60) -> 0 | N60: =IFERROR(IF(G60="","",M60/G60),"") | S60: =IFERROR(VLOOKUP(H60,Settings!B14:C25,2,FALSE()),0) -> 0
A61: =IF(B61="","",ROW()-3) | I61: =IF(G61="",0,G61*S61) -> 0 | K61: =IF(G61="",0,G61-I61-IF(J61="",0,J61)) -> 0 | L61: =IF(O61="",0,IFERROR(INDEX(Purchases!I:I,MATCH(O61*1,Purchases!A:A,0)),0)) -> 0 | M61: =IF(G61="",0,K61-L61) -> 0 | N61: =IFERROR(IF(G61="","",M61/G61),"") | S61: =IFERROR(VLOOKUP(H61,Settings!B14:C25,2,FALSE()),0) -> 0
A62: =IF(B62="","",ROW()-3) | I62: =IF(G62="",0,G62*S62) -> 0 | K62: =IF(G62="",0,G62-I62-IF(J62="",0,J62)) -> 0 | L62: =IF(O62="",0,IFERROR(INDEX(Purchases!I:I,MATCH(O62*1,Purchases!A:A,0)),0)) -> 0 | M62: =IF(G62="",0,K62-L62) -> 0 | N62: =IFERROR(IF(G62="","",M62/G62),"") | S62: =IFERROR(VLOOKUP(H62,Settings!B14:C25,2,FALSE()),0) -> 0
A63: =IF(B63="","",ROW()-3) | I63: =IF(G63="",0,G63*S63) -> 0 | K63: =IF(G63="",0,G63-I63-IF(J63="",0,J63)) -> 0 | L63: =IF(O63="",0,IFERROR(INDEX(Purchases!I:I,MATCH(O63*1,Purchases!A:A,0)),0)) -> 0 | M63: =IF(G63="",0,K63-L63) -> 0 | N63: =IFERROR(IF(G63="","",M63/G63),"") | S63: =IFERROR(VLOOKUP(H63,Settings!B14:C25,2,FALSE()),0) -> 0
A64: =IF(B64="","",ROW()-3) | I64: =IF(G64="",0,G64*S64) -> 0 | K64: =IF(G64="",0,G64-I64-IF(J64="",0,J64)) -> 0 | L64: =IF(O64="",0,IFERROR(INDEX(Purchases!I:I,MATCH(O64*1,Purchases!A:A,0)),0)) -> 0 | M64: =IF(G64="",0,K64-L64) -> 0 | N64: =IFERROR(IF(G64="","",M64/G64),"") | S64: =IFERROR(VLOOKUP(H64,Settings!B14:C25,2,FALSE()),0) -> 0
A65: =IF(B65="","",ROW()-3) | I65: =IF(G65="",0,G65*S65) -> 0 | K65: =IF(G65="",0,G65-I65-IF(J65="",0,J65)) -> 0 | L65: =IF(O65="",0,IFERROR(INDEX(Purchases!I:I,MATCH(O65*1,Purchases!A:A,0)),0)) -> 0 | M65: =IF(G65="",0,K65-L65) -> 0 | N65: =IFERROR(IF(G65="","",M65/G65),"") | S65: =IFERROR(VLOOKUP(H65,Settings!B14:C25,2,FALSE()),0) -> 0
A66: =IF(B66="","",ROW()-3) | I66: =IF(G66="",0,G66*S66) -> 0 | K66: =IF(G66="",0,G66-I66-IF(J66="",0,J66)) -> 0 | L66: =IF(O66="",0,IFERROR(INDEX(Purchases!I:I,MATCH(O66*1,Purchases!A:A,0)),0)) -> 0 | M66: =IF(G66="",0,K66-L66) -> 0 | N66: =IFERROR(IF(G66="","",M66/G66),"") | S66: =IFERROR(VLOOKUP(H66,Settings!B14:C25,2,FALSE()),0) -> 0
A67: =IF(B67="","",ROW()-3) | I67: =IF(G67="",0,G67*S67) -> 0 | K67: =IF(G67="",0,G67-I67-IF(J67="",0,J67)) -> 0 | L67: =IF(O67="",0,IFERROR(INDEX(Purchases!I:I,MATCH(O67*1,Purchases!A:A,0)),0)) -> 0 | M67: =IF(G67="",0,K67-L67) -> 0 | N67: =IFERROR(IF(G67="","",M67/G67),"") | S67: =IFERROR(VLOOKUP(H67,Settings!B14:C25,2,FALSE()),0) -> 0
A68: =IF(B68="","",ROW()-3) | I68: =IF(G68="",0,G68*S68) -> 0 | K68: =IF(G68="",0,G68-I68-IF(J68="",0,J68)) -> 0 | L68: =IF(O68="",0,IFERROR(INDEX(Purchases!I:I,MATCH(O68*1,Purchases!A:A,0)),0)) -> 0 | M68: =IF(G68="",0,K68-L68) -> 0 | N68: =IFERROR(IF(G68="","",M68/G68),"") | S68: =IFERROR(VLOOKUP(H68,Settings!B14:C25,2,FALSE()),0) -> 0
A69: =IF(B69="","",ROW()-3) | I69: =IF(G69="",0,G69*S69) -> 0 | K69: =IF(G69="",0,G69-I69-IF(J69="",0,J69)) -> 0 | L69: =IF(O69="",0,IFERROR(INDEX(Purchases!I:I,MATCH(O69*1,Purchases!A:A,0)),0)) -> 0 | M69: =IF(G69="",0,K69-L69) -> 0 | N69: =IFERROR(IF(G69="","",M69/G69),"") | S69: =IFERROR(VLOOKUP(H69,Settings!B14:C25,2,FALSE()),0) -> 0
A70: =IF(B70="","",ROW()-3) | I70: =IF(G70="",0,G70*S70) -> 0 | K70: =IF(G70="",0,G70-I70-IF(J70="",0,J70)) -> 0 | L70: =IF(O70="",0,IFERROR(INDEX(Purchases!I:I,MATCH(O70*1,Purchases!A:A,0)),0)) -> 0 | M70: =IF(G70="",0,K70-L70) -> 0 | N70: =IFERROR(IF(G70="","",M70/G70),"") | S70: =IFERROR(VLOOKUP(H70,Settings!B14:C25,2,FALSE()),0) -> 0
A71: =IF(B71="","",ROW()-3) | I71: =IF(G71="",0,G71*S71) -> 0 | K71: =IF(G71="",0,G71-I71-IF(J71="",0,J71)) -> 0 | L71: =IF(O71="",0,IFERROR(INDEX(Purchases!I:I,MATCH(O71*1,Purchases!A:A,0)),0)) -> 0 | M71: =IF(G71="",0,K71-L71) -> 0 | N71: =IFERROR(IF(G71="","",M71/G71),"") | S71: =IFERROR(VLOOKUP(H71,Settings!B14:C25,2,FALSE()),0) -> 0
A72: =IF(B72="","",ROW()-3) | I72: =IF(G72="",0,G72*S72) -> 0 | K72: =IF(G72="",0,G72-I72-IF(J72="",0,J72)) -> 0 | L72: =IF(O72="",0,IFERROR(INDEX(Purchases!I:I,MATCH(O72*1,Purchases!A:A,0)),0)) -> 0 | M72: =IF(G72="",0,K72-L72) -> 0 | N72: =IFERROR(IF(G72="","",M72/G72),"") | S72: =IFERROR(VLOOKUP(H72,Settings!B14:C25,2,FALSE()),0) -> 0
A73: =IF(B73="","",ROW()-3) | I73: =IF(G73="",0,G73*S73) -> 0 | K73: =IF(G73="",0,G73-I73-IF(J73="",0,J73)) -> 0 | L73: =IF(O73="",0,IFERROR(INDEX(Purchases!I:I,MATCH(O73*1,Purchases!A:A,0)),0)) -> 0 | M73: =IF(G73="",0,K73-L73) -> 0 | N73: =IFERROR(IF(G73="","",M73/G73),"") | S73: =IFERROR(VLOOKUP(H73,Settings!B14:C25,2,FALSE()),0) -> 0
A74: =IF(B74="","",ROW()-3) | I74: =IF(G74="",0,G74*S74) -> 0 | K74: =IF(G74="",0,G74-I74-IF(J74="",0,J74)) -> 0 | L74: =IF(O74="",0,IFERROR(INDEX(Purchases!I:I,MATCH(O74*1,Purchases!A:A,0)),0)) -> 0 | M74: =IF(G74="",0,K74-L74) -> 0 | N74: =IFERROR(IF(G74="","",M74/G74),"") | S74: =IFERROR(VLOOKUP(H74,Settings!B14:C25,2,FALSE()),0) -> 0
A75: =IF(B75="","",ROW()-3) | I75: =IF(G75="",0,G75*S75) -> 0 | K75: =IF(G75="",0,G75-I75-IF(J75="",0,J75)) -> 0 | L75: =IF(O75="",0,IFERROR(INDEX(Purchases!I:I,MATCH(O75*1,Purchases!A:A,0)),0)) -> 0 | M75: =IF(G75="",0,K75-L75) -> 0 | N75: =IFERROR(IF(G75="","",M75/G75),"") | S75: =IFERROR(VLOOKUP(H75,Settings!B14:C25,2,FALSE()),0) -> 0
A76: =IF(B76="","",ROW()-3) | I76: =IF(G76="",0,G76*S76) -> 0 | K76: =IF(G76="",0,G76-I76-IF(J76="",0,J76)) -> 0 | L76: =IF(O76="",0,IFERROR(INDEX(Purchases!I:I,MATCH(O76*1,Purchases!A:A,0)),0)) -> 0 | M76: =IF(G76="",0,K76-L76) -> 0 | N76: =IFERROR(IF(G76="","",M76/G76),"") | S76: =IFERROR(VLOOKUP(H76,Settings!B14:C25,2,FALSE()),0) -> 0
A77: =IF(B77="","",ROW()-3) | I77: =IF(G77="",0,G77*S77) -> 0 | K77: =IF(G77="",0,G77-I77-IF(J77="",0,J77)) -> 0 | L77: =IF(O77="",0,IFERROR(INDEX(Purchases!I:I,MATCH(O77*1,Purchases!A:A,0)),0)) -> 0 | M77: =IF(G77="",0,K77-L77) -> 0 | N77: =IFERROR(IF(G77="","",M77/G77),"") | S77: =IFERROR(VLOOKUP(H77,Settings!B14:C25,2,FALSE()),0) -> 0
A78: =IF(B78="","",ROW()-3) | I78: =IF(G78="",0,G78*S78) -> 0 | K78: =IF(G78="",0,G78-I78-IF(J78="",0,J78)) -> 0 | L78: =IF(O78="",0,IFERROR(INDEX(Purchases!I:I,MATCH(O78*1,Purchases!A:A,0)),0)) -> 0 | M78: =IF(G78="",0,K78-L78) -> 0 | N78: =IFERROR(IF(G78="","",M78/G78),"") | S78: =IFERROR(VLOOKUP(H78,Settings!B14:C25,2,FALSE()),0) -> 0
A79: =IF(B79="","",ROW()-3) | I79: =IF(G79="",0,G79*S79) -> 0 | K79: =IF(G79="",0,G79-I79-IF(J79="",0,J79)) -> 0 | L79: =IF(O79="",0,IFERROR(INDEX(Purchases!I:I,MATCH(O79*1,Purchases!A:A,0)),0)) -> 0 | M79: =IF(G79="",0,K79-L79) -> 0 | N79: =IFERROR(IF(G79="","",M79/G79),"") | S79: =IFERROR(VLOOKUP(H79,Settings!B14:C25,2,FALSE()),0) -> 0
A80: =IF(B80="","",ROW()-3) | I80: =IF(G80="",0,G80*S80) -> 0 | K80: =IF(G80="",0,G80-I80-IF(J80="",0,J80)) -> 0 | L80: =IF(O80="",0,IFERROR(INDEX(Purchases!I:I,MATCH(O80*1,Purchases!A:A,0)),0)) -> 0 | M80: =IF(G80="",0,K80-L80) -> 0 | N80: =IFERROR(IF(G80="","",M80/G80),"") | S80: =IFERROR(VLOOKUP(H80,Settings!B14:C25,2,FALSE()),0) -> 0
A81: =IF(B81="","",ROW()-3) | I81: =IF(G81="",0,G81*S81) -> 0 | K81: =IF(G81="",0,G81-I81-IF(J81="",0,J81)) -> 0 | L81: =IF(O81="",0,IFERROR(INDEX(Purchases!I:I,MATCH(O81*1,Purchases!A:A,0)),0)) -> 0 | M81: =IF(G81="",0,K81-L81) -> 0 | N81: =IFERROR(IF(G81="","",M81/G81),"") | S81: =IFERROR(VLOOKUP(H81,Settings!B14:C25,2,FALSE()),0) -> 0
A82: =IF(B82="","",ROW()-3) | I82: =IF(G82="",0,G82*S82) -> 0 | K82: =IF(G82="",0,G82-I82-IF(J82="",0,J82)) -> 0 | L82: =IF(O82="",0,IFERROR(INDEX(Purchases!I:I,MATCH(O82*1,Purchases!A:A,0)),0)) -> 0 | M82: =IF(G82="",0,K82-L82) -> 0 | N82: =IFERROR(IF(G82="","",M82/G82),"") | S82: =IFERROR(VLOOKUP(H82,Settings!B14:C25,2,FALSE()),0) -> 0
A83: =IF(B83="","",ROW()-3) | I83: =IF(G83="",0,G83*S83) -> 0 | K83: =IF(G83="",0,G83-I83-IF(J83="",0,J83)) -> 0 | L83: =IF(O83="",0,IFERROR(INDEX(Purchases!I:I,MATCH(O83*1,Purchases!A:A,0)),0)) -> 0 | M83: =IF(G83="",0,K83-L83) -> 0 | N83: =IFERROR(IF(G83="","",M83/G83),"") | S83: =IFERROR(VLOOKUP(H83,Settings!B14:C25,2,FALSE()),0) -> 0
A84: =IF(B84="","",ROW()-3) | I84: =IF(G84="",0,G84*S84) -> 0 | K84: =IF(G84="",0,G84-I84-IF(J84="",0,J84)) -> 0 | L84: =IF(O84="",0,IFERROR(INDEX(Purchases!I:I,MATCH(O84*1,Purchases!A:A,0)),0)) -> 0 | M84: =IF(G84="",0,K84-L84) -> 0 | N84: =IFERROR(IF(G84="","",M84/G84),"") | S84: =IFERROR(VLOOKUP(H84,Settings!B14:C25,2,FALSE()),0) -> 0
A85: =IF(B85="","",ROW()-3) | I85: =IF(G85="",0,G85*S85) -> 0 | K85: =IF(G85="",0,G85-I85-IF(J85="",0,J85)) -> 0 | L85: =IF(O85="",0,IFERROR(INDEX(Purchases!I:I,MATCH(O85*1,Purchases!A:A,0)),0)) -> 0 | M85: =IF(G85="",0,K85-L85) -> 0 | N85: =IFERROR(IF(G85="","",M85/G85),"") | S85: =IFERROR(VLOOKUP(H85,Settings!B14:C25,2,FALSE()),0) -> 0
A86: =IF(B86="","",ROW()-3) | I86: =IF(G86="",0,G86*S86) -> 0 | K86: =IF(G86="",0,G86-I86-IF(J86="",0,J86)) -> 0 | L86: =IF(O86="",0,IFERROR(INDEX(Purchases!I:I,MATCH(O86*1,Purchases!A:A,0)),0)) -> 0 | M86: =IF(G86="",0,K86-L86) -> 0 | N86: =IFERROR(IF(G86="","",M86/G86),"") | S86: =IFERROR(VLOOKUP(H86,Settings!B14:C25,2,FALSE()),0) -> 0
A87: =IF(B87="","",ROW()-3) | I87: =IF(G87="",0,G87*S87) -> 0 | K87: =IF(G87="",0,G87-I87-IF(J87="",0,J87)) -> 0 | L87: =IF(O87="",0,IFERROR(INDEX(Purchases!I:I,MATCH(O87*1,Purchases!A:A,0)),0)) -> 0 | M87: =IF(G87="",0,K87-L87) -> 0 | N87: =IFERROR(IF(G87="","",M87/G87),"") | S87: =IFERROR(VLOOKUP(H87,Settings!B14:C25,2,FALSE()),0) -> 0
A88: =IF(B88="","",ROW()-3) | I88: =IF(G88="",0,G88*S88) -> 0 | K88: =IF(G88="",0,G88-I88-IF(J88="",0,J88)) -> 0 | L88: =IF(O88="",0,IFERROR(INDEX(Purchases!I:I,MATCH(O88*1,Purchases!A:A,0)),0)) -> 0 | M88: =IF(G88="",0,K88-L88) -> 0 | N88: =IFERROR(IF(G88="","",M88/G88),"") | S88: =IFERROR(VLOOKUP(H88,Settings!B14:C25,2,FALSE()),0) -> 0
A89: =IF(B89="","",ROW()-3) | I89: =IF(G89="",0,G89*S89) -> 0 | K89: =IF(G89="",0,G89-I89-IF(J89="",0,J89)) -> 0 | L89: =IF(O89="",0,IFERROR(INDEX(Purchases!I:I,MATCH(O89*1,Purchases!A:A,0)),0)) -> 0 | M89: =IF(G89="",0,K89-L89) -> 0 | N89: =IFERROR(IF(G89="","",M89/G89),"") | S89: =IFERROR(VLOOKUP(H89,Settings!B14:C25,2,FALSE()),0) -> 0
A90: =IF(B90="","",ROW()-3) | I90: =IF(G90="",0,G90*S90) -> 0 | K90: =IF(G90="",0,G90-I90-IF(J90="",0,J90)) -> 0 | L90: =IF(O90="",0,IFERROR(INDEX(Purchases!I:I,MATCH(O90*1,Purchases!A:A,0)),0)) -> 0 | M90: =IF(G90="",0,K90-L90) -> 0 | N90: =IFERROR(IF(G90="","",M90/G90),"") | S90: =IFERROR(VLOOKUP(H90,Settings!B14:C25,2,FALSE()),0) -> 0
A91: =IF(B91="","",ROW()-3) | I91: =IF(G91="",0,G91*S91) -> 0 | K91: =IF(G91="",0,G91-I91-IF(J91="",0,J91)) -> 0 | L91: =IF(O91="",0,IFERROR(INDEX(Purchases!I:I,MATCH(O91*1,Purchases!A:A,0)),0)) -> 0 | M91: =IF(G91="",0,K91-L91) -> 0 | N91: =IFERROR(IF(G91="","",M91/G91),"") | S91: =IFERROR(VLOOKUP(H91,Settings!B14:C25,2,FALSE()),0) -> 0
A92: =IF(B92="","",ROW()-3) | I92: =IF(G92="",0,G92*S92) -> 0 | K92: =IF(G92="",0,G92-I92-IF(J92="",0,J92)) -> 0 | L92: =IF(O92="",0,IFERROR(INDEX(Purchases!I:I,MATCH(O92*1,Purchases!A:A,0)),0)) -> 0 | M92: =IF(G92="",0,K92-L92) -> 0 | N92: =IFERROR(IF(G92="","",M92/G92),"") | S92: =IFERROR(VLOOKUP(H92,Settings!B14:C25,2,FALSE()),0) -> 0
A93: =IF(B93="","",ROW()-3) | I93: =IF(G93="",0,G93*S93) -> 0 | K93: =IF(G93="",0,G93-I93-IF(J93="",0,J93)) -> 0 | L93: =IF(O93="",0,IFERROR(INDEX(Purchases!I:I,MATCH(O93*1,Purchases!A:A,0)),0)) -> 0 | M93: =IF(G93="",0,K93-L93) -> 0 | N93: =IFERROR(IF(G93="","",M93/G93),"") | S93: =IFERROR(VLOOKUP(H93,Settings!B14:C25,2,FALSE()),0) -> 0
A94: =IF(B94="","",ROW()-3) | I94: =IF(G94="",0,G94*S94) -> 0 | K94: =IF(G94="",0,G94-I94-IF(J94="",0,J94)) -> 0 | L94: =IF(O94="",0,IFERROR(INDEX(Purchases!I:I,MATCH(O94*1,Purchases!A:A,0)),0)) -> 0 | M94: =IF(G94="",0,K94-L94) -> 0 | N94: =IFERROR(IF(G94="","",M94/G94),"") | S94: =IFERROR(VLOOKUP(H94,Settings!B14:C25,2,FALSE()),0) -> 0
A95: =IF(B95="","",ROW()-3) | I95: =IF(G95="",0,G95*S95) -> 0 | K95: =IF(G95="",0,G95-I95-IF(J95="",0,J95)) -> 0 | L95: =IF(O95="",0,IFERROR(INDEX(Purchases!I:I,MATCH(O95*1,Purchases!A:A,0)),0)) -> 0 | M95: =IF(G95="",0,K95-L95) -> 0 | N95: =IFERROR(IF(G95="","",M95/G95),"") | S95: =IFERROR(VLOOKUP(H95,Settings!B14:C25,2,FALSE()),0) -> 0
A96: =IF(B96="","",ROW()-3) | I96: =IF(G96="",0,G96*S96) -> 0 | K96: =IF(G96="",0,G96-I96-IF(J96="",0,J96)) -> 0 | L96: =IF(O96="",0,IFERROR(INDEX(Purchases!I:I,MATCH(O96*1,Purchases!A:A,0)),0)) -> 0 | M96: =IF(G96="",0,K96-L96) -> 0 | N96: =IFERROR(IF(G96="","",M96/G96),"") | S96: =IFERROR(VLOOKUP(H96,Settings!B14:C25,2,FALSE()),0) -> 0
A97: =IF(B97="","",ROW()-3) | I97: =IF(G97="",0,G97*S97) -> 0 | K97: =IF(G97="",0,G97-I97-IF(J97="",0,J97)) -> 0 | L97: =IF(O97="",0,IFERROR(INDEX(Purchases!I:I,MATCH(O97*1,Purchases!A:A,0)),0)) -> 0 | M97: =IF(G97="",0,K97-L97) -> 0 | N97: =IFERROR(IF(G97="","",M97/G97),"") | S97: =IFERROR(VLOOKUP(H97,Settings!B14:C25,2,FALSE()),0) -> 0
A98: =IF(B98="","",ROW()-3) | I98: =IF(G98="",0,G98*S98) -> 0 | K98: =IF(G98="",0,G98-I98-IF(J98="",0,J98)) -> 0 | L98: =IF(O98="",0,IFERROR(INDEX(Purchases!I:I,MATCH(O98*1,Purchases!A:A,0)),0)) -> 0 | M98: =IF(G98="",0,K98-L98) -> 0 | N98: =IFERROR(IF(G98="","",M98/G98),"") | S98: =IFERROR(VLOOKUP(H98,Settings!B14:C25,2,FALSE()),0) -> 0
A99: =IF(B99="","",ROW()-3) | I99: =IF(G99="",0,G99*S99) -> 0 | K99: =IF(G99="",0,G99-I99-IF(J99="",0,J99)) -> 0 | L99: =IF(O99="",0,IFERROR(INDEX(Purchases!I:I,MATCH(O99*1,Purchases!A:A,0)),0)) -> 0 | M99: =IF(G99="",0,K99-L99) -> 0 | N99: =IFERROR(IF(G99="","",M99/G99),"") | S99: =IFERROR(VLOOKUP(H99,Settings!B14:C25,2,FALSE()),0) -> 0
A100: =IF(B100="","",ROW()-3) | I100: =IF(G100="",0,G100*S100) -> 0 | K100: =IF(G100="",0,G100-I100-IF(J100="",0,J100)) -> 0 | L100: =IF(O100="",0,IFERROR(INDEX(Purchases!I:I,MATCH(O100*1,Purchases!A:A,0)),0)) -> 0 | M100: =IF(G100="",0,K100-L100) -> 0 | N100: =IFERROR(IF(G100="","",M100/G100),"") | S100: =IFERROR(VLOOKUP(H100,Settings!B14:C25,2,FALSE()),0) -> 0
...

Sheet Settings
B2: SETTINGS & CONFIGURATION
B3: v26.0 — Configure your tracker below
B5: GENERAL | F5: QUICK REFERENCE
B6: Your Name / Shop Name | F6: Pack Opening Workflow:
B7: Currency | C7: AUD | F7: 1. Log sealed product in Purchases
B8: Country | C8: Australia | F8: 2. Set Status = "Opened" when opened
B9: Tracker Version | C9: v26.0 | F9: 3. Add pulled cards as new Purchase rows
F10: 4. Set Category = "Single Card"
F11: 5. Enter Parent ID = original purchase ID
B12: SELLING PLATFORMS & FEES | F12: 6. Cost basis = Pack cost ÷ cards pulled
B13: Platform | C13: Fee % | D13: Notes
B14: eBay AU | C14: 0.1325 | D14: TCG cards final value fee | F14: Raw → Slab Workflow:
B15: eBay US | C15: 0.1325 | D15: TCG cards final value fee | F15: 1. Card exists in Purchases (Single Card)
B16: Whatnot | C16: 0.109 | D16: 8% commission + 2.9% processing | F16: 2. Add grading fee as "Grading Fees" row
B17: Facebook Marketplace | C17: 0 | D17: Free for local pickup | F17: 3. Set original card Status = "Graded"
B18: TCGPlayer | C18: 0.1089 | D18: Standard seller level | F18: 4. Sell in Sales as "Graded Card"
B19: Gumtree | C19: 0 | D19: Free listings | F19: 5. COGS = card cost + grading fee
B20: Mercari | C20: 0.1 | D20: 10% flat fee
B21: CardMarket | C21: 0.05 | D21: EU market, varies by level | F21: Selling Workflow:
B22: Direct/Local | C22: 0 | D22: No fees for direct sales | F22: 1. Enter sale in Sales tab
B23: Shopify | C23: 0.029 | D23: 2.9% + payment processing | F23: 2. Select Platform (fee auto-calculated)
B24: Payhip | C24: 0.05 | D24: 5% on free plan | F24: 3. Enter Purchase Ref ID to link COGS
B25: Other | C25: 0 | D25: Enter custom fee | F25: 4. Profit auto-calculates
F26: 5. Update Purchase status to "Sold"
B28: MARKET PRICE APIs
B29: API Provider | C29: API Key | D29: Status / Notes
B30: PokemonTCG.io | D30: Free tier: 20K req/day. Get key: pokemontcg.io
B31: TCGdex | D31: FREE - No key needed. Cardmarket + TCGPlayer
B32: PokemonPriceTracker | D32: Free tier: limited. Best pricing + PSA data
B33: PriceCharting | D33: Historical pricing. Sealed products. Optional
B34: Custom API | D34: Add your own API endpoint
B36: Active Price Source | C36: PokemonTCG.io
B40: VERSION & DATA MIGRATION
B41: Current Version | C41: v26.0
B42: Last Migration Date | C42: N/A - First Install
B43: Data Export Format | C43: JSON
B45: ⚡ MIGRATION: Use Apps Script menu → Kollekt → Export Data to save as JSON.
B46: ⚡ IMPORT: In the new version, use Kollekt → Import Data to restore.
B47: ⚡ RESET: Use Kollekt → Reset Tracker to clear all data and restart.

Sheet Guide
B2: KOLLEKT.GG TRACKER — GETTING STARTED GUIDE
B5: WELCOME TO YOUR FINANCIAL TRACKER
B6: This spreadsheet tracks every dollar in and out of your Pokemon TCG hobby/business.
B7: It is NOT a collection tracker — it is a FINANCIAL tracker for serious collector-resellers.
B9: STEP 1: CONFIGURE SETTINGS
B10: → Go to the Settings tab
B11: → Enter your name/shop name
B12: → Select your currency (AUD default)
B13: → Review and adjust platform fee percentages
B14: → Add API keys if you want market price lookups (optional)
B16: STEP 2: INSTALL APPS SCRIPT (Google Sheets only)
B17: → Open Extensions → Apps Script
... B68: Report issues: kollekt.gg
